lab4/Bitonic_sort2.v
`timescale 1ns / 1ps

module Bitonic_sort2(a, b, max, min);
    input a;
    input b;
    output max;
    output min;

    assign max = a | b;
    assign min = a & b;

endmodule

lab4/Bitonic_sort4.v
`timescale 1ns / 1ps

module Bitonic_sort4(in, out);
    input [3:0] in;
    output [3:0] out;

    wire [3:0] AtoB;
    wire [3:0] BtoC;

    Bitonic_sort2 a0(.a(in[0]), .b(in[1]), .min(AtoB[0]), .max(AtoB[1]));
    Bitonic_sort2 a1(.a(in[2]), .b(in[3]), .min(AtoB[3]), .max(AtoB[2]));

    Bitonic_sort2 b0(.a(AtoB[0]), .b(AtoB[2]), .min(BtoC[0]), .max(BtoC[2]));
    Bitonic_sort2 b1(.a(AtoB[1]), .b(AtoB[3]), .min(BtoC[1]), .max(BtoC[3]));

    Bitonic_sort2 c0(.a(BtoC[0]), .b(BtoC[1]), .min(out[0]), .max(out[1]));
    Bitonic_sort2 c1(.a(BtoC[2]), .b(BtoC[3]), .min(out[2]), .max(out[3]));

endmodule

lab4/Bitonic_sort8.v
`timescale 1ns / 1ps

module Bitonic_sort8(in, out);
    input [7:0] in;
    output [7:0] out;

    wire [7:0] AtoB;
    wire [7:0] BtoC;
    wire [7:0] CtoD;

    Bitonic_sort4 a0(.in(in[3:0]), .out(AtoB[3:0]));
    Bitonic_sort4 a1(.in(in[7:4]), .out({AtoB[4], AtoB[5], AtoB[6], AtoB[7]}));

    Bitonic_sort2 b0(.a(AtoB[0]), .b(AtoB[4]), .min(BtoC[0]), .max(BtoC[4]));
    Bitonic_sort2 b1(.a(AtoB[1]), .b(AtoB[5]), .min(BtoC[1]), .max(BtoC[5]));
    Bitonic_sort2 b2(.a(AtoB[2]), .b(AtoB[6]), .min(BtoC[2]), .max(BtoC[6]));
    Bitonic_sort2 b3(.a(AtoB[3]), .b(AtoB[7]), .min(BtoC[3]), .max(BtoC[7]));
    

    Bitonic_sort2 c0(.a(BtoC[0]), .b(BtoC[2]), .min(CtoD[0]), .max(CtoD[2]));
    Bitonic_sort2 c1(.a(BtoC[1]), .b(BtoC[3]), .min(CtoD[1]), .max(CtoD[3]));
    Bitonic_sort2 c2(.a(BtoC[4]), .b(BtoC[6]), .min(CtoD[4]), .max(CtoD[6]));
    Bitonic_sort2 c3(.a(BtoC[5]), .b(BtoC[7]), .min(CtoD[5]), .max(CtoD[7]));


    Bitonic_sort2 d0(.a(CtoD[0]), .b(CtoD[1]), .min(out[0]), .max(out[1]));
    Bitonic_sort2 d1(.a(CtoD[2]), .b(CtoD[3]), .min(out[2]), .max(out[3]));
    Bitonic_sort2 d2(.a(CtoD[4]), .b(CtoD[5]), .min(out[4]), .max(out[5]));
    Bitonic_sort2 d3(.a(CtoD[6]), .b(CtoD[7]), .min(out[6]), .max(out[7]));    

endmodule

lab4/Bitonic_sort16.v
`timescale 1ns / 1ps

module Bitonic_sort16(in, out);
    input [15:0] in;
    output [15:0] out;

    wire [15:0] AtoB;
    wire [15:0] BtoC;
    wire [15:0] CtoD;
    wire [15:0] DtoE;

    Bitonic_sort8 a0(.in(in[7:0]), .out(AtoB[7:0]));
    Bitonic_sort8 a1(.in(in[15:8]), 
                     .out({AtoB[8], AtoB[9], AtoB[10], AtoB[11], 
                           AtoB[12], AtoB[13], AtoB[14], AtoB[15]}));



    Bitonic_sort2 b0(.a(AtoB[0]), .b(AtoB[8]), .min(BtoC[0]), .max(BtoC[8]));
    Bitonic_sort2 b1(.a(AtoB[1]), .b(AtoB[9]), .min(BtoC[1]), .max(BtoC[9]));
    Bitonic_sort2 b2(.a(AtoB[2]), .b(AtoB[10]), .min(BtoC[2]), .max(BtoC[10]));
    Bitonic_sort2 b3(.a(AtoB[3]), .b(AtoB[11]), .min(BtoC[3]), .max(BtoC[11]));
    Bitonic_sort2 b4(.a(AtoB[4]), .b(AtoB[12]), .min(BtoC[4]), .max(BtoC[12]));
    Bitonic_sort2 b5(.a(AtoB[5]), .b(AtoB[13]), .min(BtoC[5]), .max(BtoC[13]));
    Bitonic_sort2 b6(.a(AtoB[6]), .b(AtoB[14]), .min(BtoC[6]), .max(BtoC[14]));
    Bitonic_sort2 b7(.a(AtoB[7]), .b(AtoB[15]), .min(BtoC[7]), .max(BtoC[15]));
   


    Bitonic_sort2 c0(.a(BtoC[0]), .b(BtoC[4]), .min(CtoD[0]), .max(CtoD[4]));
    Bitonic_sort2 c1(.a(BtoC[1]), .b(BtoC[5]), .min(CtoD[1]), .max(CtoD[5]));
    Bitonic_sort2 c2(.a(BtoC[2]), .b(BtoC[6]), .min(CtoD[2]), .max(CtoD[6]));
    Bitonic_sort2 c3(.a(BtoC[3]), .b(BtoC[7]), .min(CtoD[3]), .max(CtoD[7]));

    Bitonic_sort2 c4(.a(BtoC[8]), .b(BtoC[12]), .min(CtoD[8]), .max(CtoD[12]));
    Bitonic_sort2 c5(.a(BtoC[9]), .b(BtoC[13]), .min(CtoD[9]), .max(CtoD[13]));
    Bitonic_sort2 c6(.a(BtoC[10]), .b(BtoC[14]), .min(CtoD[10]), .max(CtoD[14]));
    Bitonic_sort2 c7(.a(BtoC[11]), .b(BtoC[15]), .min(CtoD[11]), .max(CtoD[15]));



    Bitonic_sort2 d0(.a(CtoD[0]), .b(CtoD[2]), .min(DtoE[0]), .max(DtoE[2]));
    Bitonic_sort2 d1(.a(CtoD[1]), .b(CtoD[3]), .min(DtoE[1]), .max(DtoE[3]));

    Bitonic_sort2 d2(.a(CtoD[4]), .b(CtoD[6]), .min(DtoE[4]), .max(DtoE[6]));
    Bitonic_sort2 d3(.a(CtoD[5]), .b(CtoD[7]), .min(DtoE[5]), .max(DtoE[7]));    

    Bitonic_sort2 d4(.a(CtoD[8]), .b(CtoD[10]), .min(DtoE[8]), .max(DtoE[10]));
    Bitonic_sort2 d5(.a(CtoD[9]), .b(CtoD[11]), .min(DtoE[9]), .max(DtoE[11]));

    Bitonic_sort2 d6(.a(CtoD[12]), .b(CtoD[14]), .min(DtoE[12]), .max(DtoE[14]));
    Bitonic_sort2 d7(.a(CtoD[13]), .b(CtoD[15]), .min(DtoE[13]), .max(DtoE[15]));





    Bitonic_sort2 e0(.a(DtoE[0]), .b(DtoE[1]), .min(out[0]), .max(out[1]));
    Bitonic_sort2 e1(.a(DtoE[2]), .b(DtoE[3]), .min(out[2]), .max(out[3]));
    Bitonic_sort2 e2(.a(DtoE[4]), .b(DtoE[5]), .min(out[4]), .max(out[5]));
    Bitonic_sort2 e3(.a(DtoE[6]), .b(DtoE[7]), .min(out[6]), .max(out[7]));    
    Bitonic_sort2 e4(.a(DtoE[8]), .b(DtoE[9]), .min(out[8]), .max(out[9]));
    Bitonic_sort2 e5(.a(DtoE[10]), .b(DtoE[11]), .min(out[10]), .max(out[11]));
    Bitonic_sort2 e6(.a(DtoE[12]), .b(DtoE[13]), .min(out[12]), .max(out[13]));
    Bitonic_sort2 e7(.a(DtoE[14]), .b(DtoE[15]), .min(out[14]), .max(out[15]));

endmodule

lab4/bitonic_sort_16_test.v
// Testbench for a 16-input bitonic sorter - You don't have to modify it

// Input lines make 1->0 transitions at different times (essentially values
// ranging from 0 to 39) coming in at the 16 input lines in an unsorted manner.
// At the output of the sorter, the lines should have 1->0 transitions in
// ascending order.

`timescale 1ns / 1ps

module bitonic_sort_tb;

    reg [15:0] raw_in;
    wire [15:0] sorted_out;

    Bitonic_sort16 DUT (.out(sorted_out), .in(raw_in));

    initial
    begin

        $dumpfile("bitonic_sort_16.vcd");
        $dumpvars(0, bitonic_sort_tb);

        raw_in = ~16'b0;

        #5
        raw_in[1] = 0;

        #2
        raw_in[13] = 0;

        #3
        raw_in[5] = 0;

        #1
        raw_in[12] = 0;

        #4
        raw_in[4] = 0;

        #2
        raw_in[7] = 0;

        #3
        raw_in[3] = 0;

        #1
        raw_in[15] = 0;

        #5
        raw_in[10] = 0;
        
        #4
        raw_in[2] = 0;
        
        #5
        raw_in[8] = 0;
        
        #2
        raw_in[11] = 0;
        
        #3
        raw_in[14] = 0;
        
        #1
        raw_in[0] = 0;
        
        #2
        raw_in[6] = 0;
        
        #1
        raw_in[9] = 0;
        
        #10
        raw_in = ~16'b0;

        #200
        $finish;

    end

endmodule

lab4/bitonic_sort_16.vcd
$date
	Mon Mar 18 10:14:01 2019
$end
$version
	Icarus Verilog
$end
$timescale
	1ps
$end
$scope module bitonic_sort_tb $end
$var wire 16 ! sorted_out [15:0] $end
$var reg 16 " raw_in [15:0] $end
$scope module DUT $end
$var wire 16 # in [15:0] $end
$var wire 16 $ out [15:0] $end
$var wire 16 % DtoE [15:0] $end
$var wire 16 & CtoD [15:0] $end
$var wire 16 ' BtoC [15:0] $end
$var wire 16 ( AtoB [15:0] $end
$scope module a0 $end
$var wire 8 ) in [7:0] $end
$var wire 8 * out [7:0] $end
$var wire 8 + CtoD [7:0] $end
$var wire 8 , BtoC [7:0] $end
$var wire 8 - AtoB [7:0] $end
$scope module a0 $end
$var wire 4 . in [3:0] $end
$var wire 4 / out [3:0] $end
$var wire 4 0 BtoC [3:0] $end
$var wire 4 1 AtoB [3:0] $end
$scope module a0 $end
$var wire 1 2 a $end
$var wire 1 3 b $end
$var wire 1 4 max $end
$var wire 1 5 min $end
$upscope $end
$scope module a1 $end
$var wire 1 6 a $end
$var wire 1 7 b $end
$var wire 1 8 max $end
$var wire 1 9 min $end
$upscope $end
$scope module b0 $end
$var wire 1 : a $end
$var wire 1 ; b $end
$var wire 1 < max $end
$var wire 1 = min $end
$upscope $end
$scope module b1 $end
$var wire 1 > a $end
$var wire 1 ? b $end
$var wire 1 @ max $end
$var wire 1 A min $end
$upscope $end
$scope module c0 $end
$var wire 1 B a $end
$var wire 1 C b $end
$var wire 1 D max $end
$var wire 1 E min $end
$upscope $end
$scope module c1 $end
$var wire 1 F a $end
$var wire 1 G b $end
$var wire 1 H max $end
$var wire 1 I min $end
$upscope $end
$upscope $end
$scope module a1 $end
$var wire 4 J in [3:0] $end
$var wire 4 K out [3:0] $end
$var wire 4 L BtoC [3:0] $end
$var wire 4 M AtoB [3:0] $end
$scope module a0 $end
$var wire 1 N a $end
$var wire 1 O b $end
$var wire 1 P max $end
$var wire 1 Q min $end
$upscope $end
$scope module a1 $end
$var wire 1 R a $end
$var wire 1 S b $end
$var wire 1 T max $end
$var wire 1 U min $end
$upscope $end
$scope module b0 $end
$var wire 1 V a $end
$var wire 1 W b $end
$var wire 1 X max $end
$var wire 1 Y min $end
$upscope $end
$scope module b1 $end
$var wire 1 Z a $end
$var wire 1 [ b $end
$var wire 1 \ max $end
$var wire 1 ] min $end
$upscope $end
$scope module c0 $end
$var wire 1 ^ a $end
$var wire 1 _ b $end
$var wire 1 ` max $end
$var wire 1 a min $end
$upscope $end
$scope module c1 $end
$var wire 1 b a $end
$var wire 1 c b $end
$var wire 1 d max $end
$var wire 1 e min $end
$upscope $end
$upscope $end
$scope module b0 $end
$var wire 1 f a $end
$var wire 1 g b $end
$var wire 1 h max $end
$var wire 1 i min $end
$upscope $end
$scope module b1 $end
$var wire 1 j a $end
$var wire 1 k b $end
$var wire 1 l max $end
$var wire 1 m min $end
$upscope $end
$scope module b2 $end
$var wire 1 n a $end
$var wire 1 o b $end
$var wire 1 p max $end
$var wire 1 q min $end
$upscope $end
$scope module b3 $end
$var wire 1 r a $end
$var wire 1 s b $end
$var wire 1 t max $end
$var wire 1 u min $end
$upscope $end
$scope module c0 $end
$var wire 1 v a $end
$var wire 1 w b $end
$var wire 1 x max $end
$var wire 1 y min $end
$upscope $end
$scope module c1 $end
$var wire 1 z a $end
$var wire 1 { b $end
$var wire 1 | max $end
$var wire 1 } min $end
$upscope $end
$scope module c2 $end
$var wire 1 ~ a $end
$var wire 1 !" b $end
$var wire 1 "" max $end
$var wire 1 #" min $end
$upscope $end
$scope module c3 $end
$var wire 1 $" a $end
$var wire 1 %" b $end
$var wire 1 &" max $end
$var wire 1 '" min $end
$upscope $end
$scope module d0 $end
$var wire 1 (" a $end
$var wire 1 )" b $end
$var wire 1 *" max $end
$var wire 1 +" min $end
$upscope $end
$scope module d1 $end
$var wire 1 ," a $end
$var wire 1 -" b $end
$var wire 1 ." max $end
$var wire 1 /" min $end
$upscope $end
$scope module d2 $end
$var wire 1 0" a $end
$var wire 1 1" b $end
$var wire 1 2" max $end
$var wire 1 3" min $end
$upscope $end
$scope module d3 $end
$var wire 1 4" a $end
$var wire 1 5" b $end
$var wire 1 6" max $end
$var wire 1 7" min $end
$upscope $end
$upscope $end
$scope module a1 $end
$var wire 8 8" in [7:0] $end
$var wire 8 9" out [7:0] $end
$var wire 8 :" CtoD [7:0] $end
$var wire 8 ;" BtoC [7:0] $end
$var wire 8 <" AtoB [7:0] $end
$scope module a0 $end
$var wire 4 =" in [3:0] $end
$var wire 4 >" out [3:0] $end
$var wire 4 ?" BtoC [3:0] $end
$var wire 4 @" AtoB [3:0] $end
$scope module a0 $end
$var wire 1 A" a $end
$var wire 1 B" b $end
$var wire 1 C" max $end
$var wire 1 D" min $end
$upscope $end
$scope module a1 $end
$var wire 1 E" a $end
$var wire 1 F" b $end
$var wire 1 G" max $end
$var wire 1 H" min $end
$upscope $end
$scope module b0 $end
$var wire 1 I" a $end
$var wire 1 J" b $end
$var wire 1 K" max $end
$var wire 1 L" min $end
$upscope $end
$scope module b1 $end
$var wire 1 M" a $end
$var wire 1 N" b $end
$var wire 1 O" max $end
$var wire 1 P" min $end
$upscope $end
$scope module c0 $end
$var wire 1 Q" a $end
$var wire 1 R" b $end
$var wire 1 S" max $end
$var wire 1 T" min $end
$upscope $end
$scope module c1 $end
$var wire 1 U" a $end
$var wire 1 V" b $end
$var wire 1 W" max $end
$var wire 1 X" min $end
$upscope $end
$upscope $end
$scope module a1 $end
$var wire 4 Y" in [3:0] $end
$var wire 4 Z" out [3:0] $end
$var wire 4 [" BtoC [3:0] $end
$var wire 4 \" AtoB [3:0] $end
$scope module a0 $end
$var wire 1 ]" a $end
$var wire 1 ^" b $end
$var wire 1 _" max $end
$var wire 1 `" min $end
$upscope $end
$scope module a1 $end
$var wire 1 a" a $end
$var wire 1 b" b $end
$var wire 1 c" max $end
$var wire 1 d" min $end
$upscope $end
$scope module b0 $end
$var wire 1 e" a $end
$var wire 1 f" b $end
$var wire 1 g" max $end
$var wire 1 h" min $end
$upscope $end
$scope module b1 $end
$var wire 1 i" a $end
$var wire 1 j" b $end
$var wire 1 k" max $end
$var wire 1 l" min $end
$upscope $end
$scope module c0 $end
$var wire 1 m" a $end
$var wire 1 n" b $end
$var wire 1 o" max $end
$var wire 1 p" min $end
$upscope $end
$scope module c1 $end
$var wire 1 q" a $end
$var wire 1 r" b $end
$var wire 1 s" max $end
$var wire 1 t" min $end
$upscope $end
$upscope $end
$scope module b0 $end
$var wire 1 u" a $end
$var wire 1 v" b $end
$var wire 1 w" max $end
$var wire 1 x" min $end
$upscope $end
$scope module b1 $end
$var wire 1 y" a $end
$var wire 1 z" b $end
$var wire 1 {" max $end
$var wire 1 |" min $end
$upscope $end
$scope module b2 $end
$var wire 1 }" a $end
$var wire 1 ~" b $end
$var wire 1 !# max $end
$var wire 1 "# min $end
$upscope $end
$scope module b3 $end
$var wire 1 ## a $end
$var wire 1 $# b $end
$var wire 1 %# max $end
$var wire 1 &# min $end
$upscope $end
$scope module c0 $end
$var wire 1 '# a $end
$var wire 1 (# b $end
$var wire 1 )# max $end
$var wire 1 *# min $end
$upscope $end
$scope module c1 $end
$var wire 1 +# a $end
$var wire 1 ,# b $end
$var wire 1 -# max $end
$var wire 1 .# min $end
$upscope $end
$scope module c2 $end
$var wire 1 /# a $end
$var wire 1 0# b $end
$var wire 1 1# max $end
$var wire 1 2# min $end
$upscope $end
$scope module c3 $end
$var wire 1 3# a $end
$var wire 1 4# b $end
$var wire 1 5# max $end
$var wire 1 6# min $end
$upscope $end
$scope module d0 $end
$var wire 1 7# a $end
$var wire 1 8# b $end
$var wire 1 9# max $end
$var wire 1 :# min $end
$upscope $end
$scope module d1 $end
$var wire 1 ;# a $end
$var wire 1 <# b $end
$var wire 1 =# max $end
$var wire 1 ># min $end
$upscope $end
$scope module d2 $end
$var wire 1 ?# a $end
$var wire 1 @# b $end
$var wire 1 A# max $end
$var wire 1 B# min $end
$upscope $end
$scope module d3 $end
$var wire 1 C# a $end
$var wire 1 D# b $end
$var wire 1 E# max $end
$var wire 1 F# min $end
$upscope $end
$upscope $end
$scope module b0 $end
$var wire 1 G# a $end
$var wire 1 H# b $end
$var wire 1 I# max $end
$var wire 1 J# min $end
$upscope $end
$scope module b1 $end
$var wire 1 K# a $end
$var wire 1 L# b $end
$var wire 1 M# max $end
$var wire 1 N# min $end
$upscope $end
$scope module b2 $end
$var wire 1 O# a $end
$var wire 1 P# b $end
$var wire 1 Q# max $end
$var wire 1 R# min $end
$upscope $end
$scope module b3 $end
$var wire 1 S# a $end
$var wire 1 T# b $end
$var wire 1 U# max $end
$var wire 1 V# min $end
$upscope $end
$scope module b4 $end
$var wire 1 W# a $end
$var wire 1 X# b $end
$var wire 1 Y# max $end
$var wire 1 Z# min $end
$upscope $end
$scope module b5 $end
$var wire 1 [# a $end
$var wire 1 \# b $end
$var wire 1 ]# max $end
$var wire 1 ^# min $end
$upscope $end
$scope module b6 $end
$var wire 1 _# a $end
$var wire 1 `# b $end
$var wire 1 a# max $end
$var wire 1 b# min $end
$upscope $end
$scope module b7 $end
$var wire 1 c# a $end
$var wire 1 d# b $end
$var wire 1 e# max $end
$var wire 1 f# min $end
$upscope $end
$scope module c0 $end
$var wire 1 g# a $end
$var wire 1 h# b $end
$var wire 1 i# max $end
$var wire 1 j# min $end
$upscope $end
$scope module c1 $end
$var wire 1 k# a $end
$var wire 1 l# b $end
$var wire 1 m# max $end
$var wire 1 n# min $end
$upscope $end
$scope module c2 $end
$var wire 1 o# a $end
$var wire 1 p# b $end
$var wire 1 q# max $end
$var wire 1 r# min $end
$upscope $end
$scope module c3 $end
$var wire 1 s# a $end
$var wire 1 t# b $end
$var wire 1 u# max $end
$var wire 1 v# min $end
$upscope $end
$scope module c4 $end
$var wire 1 w# a $end
$var wire 1 x# b $end
$var wire 1 y# max $end
$var wire 1 z# min $end
$upscope $end
$scope module c5 $end
$var wire 1 {# a $end
$var wire 1 |# b $end
$var wire 1 }# max $end
$var wire 1 ~# min $end
$upscope $end
$scope module c6 $end
$var wire 1 !$ a $end
$var wire 1 "$ b $end
$var wire 1 #$ max $end
$var wire 1 $$ min $end
$upscope $end
$scope module c7 $end
$var wire 1 %$ a $end
$var wire 1 &$ b $end
$var wire 1 '$ max $end
$var wire 1 ($ min $end
$upscope $end
$scope module d0 $end
$var wire 1 )$ a $end
$var wire 1 *$ b $end
$var wire 1 +$ max $end
$var wire 1 ,$ min $end
$upscope $end
$scope module d1 $end
$var wire 1 -$ a $end
$var wire 1 .$ b $end
$var wire 1 /$ max $end
$var wire 1 0$ min $end
$upscope $end
$scope module d2 $end
$var wire 1 1$ a $end
$var wire 1 2$ b $end
$var wire 1 3$ max $end
$var wire 1 4$ min $end
$upscope $end
$scope module d3 $end
$var wire 1 5$ a $end
$var wire 1 6$ b $end
$var wire 1 7$ max $end
$var wire 1 8$ min $end
$upscope $end
$scope module d4 $end
$var wire 1 9$ a $end
$var wire 1 :$ b $end
$var wire 1 ;$ max $end
$var wire 1 <$ min $end
$upscope $end
$scope module d5 $end
$var wire 1 =$ a $end
$var wire 1 >$ b $end
$var wire 1 ?$ max $end
$var wire 1 @$ min $end
$upscope $end
$scope module d6 $end
$var wire 1 A$ a $end
$var wire 1 B$ b $end
$var wire 1 C$ max $end
$var wire 1 D$ min $end
$upscope $end
$scope module d7 $end
$var wire 1 E$ a $end
$var wire 1 F$ b $end
$var wire 1 G$ max $end
$var wire 1 H$ min $end
$upscope $end
$scope module e0 $end
$var wire 1 I$ a $end
$var wire 1 J$ b $end
$var wire 1 K$ max $end
$var wire 1 L$ min $end
$upscope $end
$scope module e1 $end
$var wire 1 M$ a $end
$var wire 1 N$ b $end
$var wire 1 O$ max $end
$var wire 1 P$ min $end
$upscope $end
$scope module e2 $end
$var wire 1 Q$ a $end
$var wire 1 R$ b $end
$var wire 1 S$ max $end
$var wire 1 T$ min $end
$upscope $end
$scope module e3 $end
$var wire 1 U$ a $end
$var wire 1 V$ b $end
$var wire 1 W$ max $end
$var wire 1 X$ min $end
$upscope $end
$scope module e4 $end
$var wire 1 Y$ a $end
$var wire 1 Z$ b $end
$var wire 1 [$ max $end
$var wire 1 \$ min $end
$upscope $end
$scope module e5 $end
$var wire 1 ]$ a $end
$var wire 1 ^$ b $end
$var wire 1 _$ max $end
$var wire 1 `$ min $end
$upscope $end
$scope module e6 $end
$var wire 1 a$ a $end
$var wire 1 b$ b $end
$var wire 1 c$ max $end
$var wire 1 d$ min $end
$upscope $end
$scope module e7 $end
$var wire 1 e$ a $end
$var wire 1 f$ b $end
$var wire 1 g$ max $end
$var wire 1 h$ min $end
$upscope $end
$upscope $end
$upscope $end
$enddefinitions $end
#0
$dumpvars
1h$
1g$
1f$
1e$
1d$
1c$
1b$
1a$
1`$
1_$
1^$
1]$
1\$
1[$
1Z$
1Y$
1X$
1W$
1V$
1U$
1T$
1S$
1R$
1Q$
1P$
1O$
1N$
1M$
1L$
1K$
1J$
1I$
1H$
1G$
1F$
1E$
1D$
1C$
1B$
1A$
1@$
1?$
1>$
1=$
1<$
1;$
1:$
19$
18$
17$
16$
15$
14$
13$
12$
11$
10$
1/$
1.$
1-$
1,$
1+$
1*$
1)$
1($
1'$
1&$
1%$
1$$
1#$
1"$
1!$
1~#
1}#
1|#
1{#
1z#
1y#
1x#
1w#
1v#
1u#
1t#
1s#
1r#
1q#
1p#
1o#
1n#
1m#
1l#
1k#
1j#
1i#
1h#
1g#
1f#
1e#
1d#
1c#
1b#
1a#
1`#
1_#
1^#
1]#
1\#
1[#
1Z#
1Y#
1X#
1W#
1V#
1U#
1T#
1S#
1R#
1Q#
1P#
1O#
1N#
1M#
1L#
1K#
1J#
1I#
1H#
1G#
1F#
1E#
1D#
1C#
1B#
1A#
1@#
1?#
1>#
1=#
1<#
1;#
1:#
19#
18#
17#
16#
15#
14#
13#
12#
11#
10#
1/#
1.#
1-#
1,#
1+#
1*#
1)#
1(#
1'#
1&#
1%#
1$#
1##
1"#
1!#
1~"
1}"
1|"
1{"
1z"
1y"
1x"
1w"
1v"
1u"
1t"
1s"
1r"
1q"
1p"
1o"
1n"
1m"
1l"
1k"
1j"
1i"
1h"
1g"
1f"
1e"
1d"
1c"
1b"
1a"
1`"
1_"
1^"
1]"
b1111 \"
b1111 ["
b1111 Z"
b1111 Y"
1X"
1W"
1V"
1U"
1T"
1S"
1R"
1Q"
1P"
1O"
1N"
1M"
1L"
1K"
1J"
1I"
1H"
1G"
1F"
1E"
1D"
1C"
1B"
1A"
b1111 @"
b1111 ?"
b1111 >"
b1111 ="
b11111111 <"
b11111111 ;"
b11111111 :"
b11111111 9"
b11111111 8"
17"
16"
15"
14"
13"
12"
11"
10"
1/"
1."
1-"
1,"
1+"
1*"
1)"
1("
1'"
1&"
1%"
1$"
1#"
1""
1!"
1~
1}
1|
1{
1z
1y
1x
1w
1v
1u
1t
1s
1r
1q
1p
1o
1n
1m
1l
1k
1j
1i
1h
1g
1f
1e
1d
1c
1b
1a
1`
1_
1^
1]
1\
1[
1Z
1Y
1X
1W
1V
1U
1T
1S
1R
1Q
1P
1O
1N
b1111 M
b1111 L
b1111 K
b1111 J
1I
1H
1G
1F
1E
1D
1C
1B
1A
1@
1?
1>
1=
1<
1;
1:
19
18
17
16
15
14
13
12
b1111 1
b1111 0
b1111 /
b1111 .
b11111111 -
b11111111 ,
b11111111 +
b11111111 *
b11111111 )
b1111111111111111 (
b1111111111111111 '
b1111111111111111 &
b1111111111111111 %
b1111111111111111 $
b1111111111111111 #
b1111111111111111 "
b1111111111111111 !
$end
#5000
b1111111111111110 !
b1111111111111110 $
0L$
0I$
b1111111111111110 %
0,$
0)$
b1111111111111110 &
0j#
0g#
b1111111111111110 '
0J#
0G#
b1111111111111110 (
b11111110 *
0+"
0("
b11111110 +
0y
0v
b11111110 ,
0i
0f
b11111110 -
b1110 /
0E
0B
b1110 0
0=
0:
b1110 1
05
03
b1101 .
b11111101 )
b1111111111111101 "
b1111111111111101 #
#7000
b1111111111111100 !
b1111111111111100 $
0K$
0J$
b1111111111111100 %
00$
0.$
b1111111111110110 &
0v#
0t#
b1111111101111110 '
0f#
0d#
b111111111111110 (
b11111110 9"
0:#
08#
b11111101 :"
0.#
0,#
b11110111 ;"
0&#
0$#
b1111111 <"
b1110 Z"
0p"
0m"
b1110 ["
0h"
0e"
b1110 \"
0`"
0^"
b1101 Y"
b11011111 8"
b1101111111111101 "
b1101111111111101 #
#10000
b1111111111111000 !
b1111111111111000 $
0P$
0N$
b1111111111110100 %
0/$
0-$
b1111111111110100 &
0n#
0k#
b1111111101111100 '
0N#
0K#
b111111111111100 (
b11111100 *
0*"
0)"
b11111100 +
0}
0{
b11110110 ,
0u
0s
b1111110 -
b1110 K
0a
0^
b1110 L
0Y
0V
b1110 M
0Q
0O
b1101 J
b11011101 )
b1101111111011101 "
b1101111111011101 #
#11000
b1111111111110000 !
b1111111111110000 $
0O$
0M$
b1111111111110000 %
0+$
0*$
b1111111111110000 &
0r#
0p#
b1111111100111100 '
0b#
0`#
b11111111111100 (
b11111100 9"
09#
07#
b11111100 :"
0*#
0(#
b11110011 ;"
0"#
0~"
b111111 <"
b1100 Z"
0o"
0n"
b1100 ["
0l"
0i"
b1100 \"
0_"
0]"
b1100 Y"
b11001111 8"
b1100111111011101 "
b1100111111011101 #
#15000
b1111111111100000 !
b1111111111100000 $
0T$
0Q$
b1111111111100000 %
04$
02$
b1111111110110000 &
0q#
0o#
b1111111100111000 '
0R#
0O#
b11111111111000 (
b11111000 *
0/"
0,"
b11111000 +
0x
0w
b11110010 ,
0q
0o
b111110 -
b1100 K
0`
0_
b1100 L
0]
0Z
b1100 M
0P
0N
b1100 J
b11001101 )
b1100111111001101 "
b1100111111001101 #
#17000
b1111111111000000 !
b1111111111000000 $
0S$
0R$
b1111111111000000 %
08$
06$
b1111111100110000 &
0u#
0s#
b1111111100110000 '
0V#
0S#
b11111111110000 (
b11110000 *
0."
0-"
b11110000 +
0|
0z
b11110000 ,
0m
0k
b11110 -
b1000 K
0e
0c
b100 L
0\
0[
b100 M
0U
0S
b100 J
b1001101 )
b1100111101001101 "
b1100111101001101 #
#20000
b1111111110000000 !
b1111111110000000 $
0X$
0U$
b1111111110000000 %
03$
01$
b1111111100100000 &
0i#
0h#
b1111111100100000 '
0Z#
0W#
b11111111100000 (
b11100000 *
03"
01"
b11010000 +
0'"
0$"
b11010000 ,
0l
0j
b11100 -
b1100 /
0D
0C
b1100 0
0A
0?
b110 1
09
07
b101 .
b1000101 )
b1100111101000101 "
b1100111101000101 #
#21000
b1111111100000000 !
b1111111100000000 $
0W$
0V$
b1111111100000000 %
07$
05$
b1111111100000000 &
0m#
0l#
b1111111100000000 '
0^#
0\#
b1111111100000 (
b11111000 9"
0>#
0<#
b11110100 :"
0-#
0+#
b11110001 ;"
0|"
0z"
b11111 <"
b1000 Z"
0t"
0r"
b100 ["
0k"
0j"
b100 \"
0d"
0b"
b100 Y"
b1001111 8"
b100111101000101 "
b100111101000101 #
#26000
b1111111000000000 !
b1111111000000000 $
0\$
0Y$
b1111111000000000 %
0<$
09$
b1111111000000000 &
0z#
0x#
b1110111100000000 '
0Y#
0X#
b111111100000 (
b11110000 9"
0=#
0;#
b11110000 :"
0)#
0'#
b11110000 ;"
0x"
0u"
b11110 <"
b1110 >"
0T"
0R"
b1101 ?"
0P"
0N"
b111 @"
0H"
0E"
b1011 ="
b1001011 8"
b100101101000101 "
b100101101000101 #
#30000
b1111110000000000 !
b1111110000000000 $
0[$
0Z$
b1111110000000000 %
0@$
0=$
b1111110000000000 &
0~#
0|#
b1100111100000000 '
0]#
0[#
b111111000000 (
b11000000 *
02"
00"
b11000000 +
0#"
0!"
b10010000 ,
0p
0n
b11000 -
b1000 /
0I
0F
b1000 0
0<
0;
b10 1
08
06
b1 .
b1000001 )
b100101101000001 "
b100101101000001 #
#35000
b1111100000000000 !
b1111100000000000 $
0`$
0^$
b1111010000000000 %
0?$
0>$
b1111010000000000 &
0($
0%$
b1100011100000000 '
0U#
0T#
b11111000000 (
b11100000 9"
0B#
0@#
b11010000 :"
06#
03#
b11010000 ;"
0{"
0y"
b11100 <"
b1100 >"
0S"
0Q"
b1100 ?"
0L"
0I"
b110 @"
0D"
0A"
b1010 ="
b1001010 8"
b100101001000001 "
b100101001000001 #
#37000
b1111000000000000 !
b1111000000000000 $
0_$
0]$
b1111000000000000 %
0;$
0:$
b1111000000000000 &
0$$
0!$
b1100001100000000 '
0Q#
0P#
b1111000000 (
b11000000 9"
0A#
0?#
b11000000 :"
02#
00#
b10010000 ;"
0!#
0}"
b11000 <"
b1000 >"
0X"
0U"
b1000 ?"
0K"
0J"
b10 @"
0G"
0F"
b10 ="
b1000010 8"
b100001001000001 "
b100001001000001 #
#40000
b1110000000000000 !
b1110000000000000 $
0d$
0b$
b1101000000000000 %
0H$
0E$
b1101000000000000 &
0}#
0{#
b1100000100000000 '
0M#
0L#
b111000000 (
b10000000 9"
0F#
0C#
b10000000 :"
01#
0/#
b10000000 ;"
0w"
0v"
b1000 <"
b0 Z"
0s"
0q"
b0 ["
0g"
0f"
b0 \"
0c"
0a"
b0 Y"
b10 8"
b1001000001 "
b1001000001 #
